{"choices":[{"id":"question1","question":"213123","options":[{"id":"A","text":"123123"},{"id":"B","text":"21312312"},{"id":"C","text":"3123"},{"id":"D","text":"123123"}]},{"id":"question1","question":"213123","options":[{"id":"A","text":"123123"},{"id":"B","text":"21312312"},{"id":"C","text":"3123"},{"id":"D","text":"123123"}]},{"id":"question1","question":"213123","options":[{"id":"A","text":"123123"},{"id":"B","text":"21312312"},{"id":"C","text":"3123"},{"id":"D","text":"123123"}]},{"id":"question1","question":"213123","options":[{"id":"A","text":"123123"},{"id":"B","text":"21312312"},{"id":"C","text":"3123"},{"id":"D","text":"123123"}]},{"id":"question1","question":"213123","options":[{"id":"A","text":"123123"},{"id":"B","text":"21312312"},{"id":"C","text":"3123"},{"id":"D","text":"123123"}]}],"choiceTotal":20,"blanks":["123123***","123123***","123123***","123123***","123123***"],"blankTotal":20,"shorts":["wiudhuiqdwhuiwqhdiuqwd","wiudhuiqdwhuiwqhdiuqwd","wiudhuiqdwhuiwqhdiuqwd","wiudhuiqdwhuiwqhdiuqwd","wiudhuiqdwhuiwqhdiuqwd"],"shortTotal":20,"programs":["nbhai ","nbhai ","nbhai "],"programTotal":40}